-- Lua Interpreter VM — Constants (Lua 5.5 aligned)
-- Value tags, opcodes (0-84), TM events, resume modes, statuses, error codes, GC state, proto flags.

local Tag = {}
Tag.NIL = 0
Tag.FALSE = 1
Tag.TRUE = 2
Tag.LIGHTUD = 3
Tag.INTEGER = 4
Tag.NUM = 5
Tag.STR = 6
Tag.TABLE = 7
Tag.LCLOSURE = 8
Tag.CCLOSURE = 9
Tag.USERDATA = 10
Tag.THREAD = 11
Tag.PROTO = 12

local Op = {}
Op.MOVE = 0
Op.LOADI = 1
Op.LOADF = 2
Op.LOADK = 3
Op.LOADKX = 4
Op.LOADFALSE = 5
Op.LFALSESKIP = 6
Op.LOADTRUE = 7
Op.LOADNIL = 8
Op.GETUPVAL = 9
Op.SETUPVAL = 10
Op.GETTABUP = 11
Op.GETTABLE = 12
Op.GETI = 13
Op.GETFIELD = 14
Op.SETTABUP = 15
Op.SETTABLE = 16
Op.SETI = 17
Op.SETTI = 17 -- backward-compatible alias for the Lua 5.5 OP_SETI spelling
Op.SETFIELD = 18
Op.NEWTABLE = 19
Op.SELF = 20
Op.ADDI = 21
Op.ADDK = 22
Op.SUBK = 23
Op.MULK = 24
Op.MODK = 25
Op.POWK = 26
Op.DIVK = 27
Op.IDIVK = 28
Op.BANDK = 29
Op.BORK = 30
Op.BXORK = 31
Op.SHLI = 32
Op.SHRI = 33
Op.ADD = 34
Op.SUB = 35
Op.MUL = 36
Op.MOD = 37
Op.POW = 38
Op.DIV = 39
Op.IDIV = 40
Op.BAND = 41
Op.BOR = 42
Op.BXOR = 43
Op.SHL = 44
Op.SHR = 45
Op.MMBIN = 46
Op.MMBINI = 47
Op.MMBINK = 48
Op.UNM = 49
Op.BNOT = 50
Op.NOT = 51
Op.LEN = 52
Op.CONCAT = 53
Op.CLOSE = 54
Op.TBC = 55
Op.JMP = 56
Op.EQ = 57
Op.LT = 58
Op.LE = 59
Op.EQK = 60
Op.EQI = 61
Op.LTI = 62
Op.LEI = 63
Op.GTI = 64
Op.GEI = 65
Op.TEST = 66
Op.TESTSET = 67
Op.CALL = 68
Op.TAILCALL = 69
Op.RETURN = 70
Op.RETURN0 = 71
Op.RETURN1 = 72
Op.FORLOOP = 73
Op.FORPREP = 74
Op.TFORPREP = 75
Op.TFORCALL = 76
Op.TFORLOOP = 77
Op.SETLIST = 78
Op.CLOSURE = 79
Op.VARARG = 80
Op.GETVARG = 81
Op.ERRNNIL = 82
Op.VARARGPREP = 83
Op.EXTRAARG = 84

local TM = {}
TM.INDEX = 0
TM.NEWINDEX = 1
TM.GC = 2
TM.MODE = 3
TM.EQ = 4
TM.ADD = 5
TM.SUB = 6
TM.MUL = 7
TM.DIV = 8
TM.MOD = 9
TM.POW = 10
TM.UNM = 11
TM.LEN = 12
TM.LT = 13
TM.LE = 14
TM.CONCAT = 15
TM.CALL = 16
TM.IDIV = 17
TM.BAND = 18
TM.BOR = 19
TM.BXOR = 20
TM.SHL = 21
TM.SHR = 22
TM.CLOSE = 23
TM.N = 24

local Resume = {}
Resume.NORMAL = 0
Resume.TAILCALL = 1
Resume.PCALL = 2
Resume.XPCALL = 3
Resume.GETTABLE_MM = 4
Resume.SETTABLE_MM = 5
Resume.BINOP_MM = 6
Resume.UNOP_MM = 7
Resume.LEN_MM = 8
Resume.CONCAT_MM = 9
Resume.EQ_MM = 10
Resume.LT_MM = 11
Resume.LE_MM = 12
Resume.CALL_MM = 13
Resume.TFORLOOP_CALL = 14
Resume.NATIVE_CONT = 15
Resume.TBC_CLOSE = 16
Resume.N = 17

local Status = {}
Status.OK = 0
Status.YIELDED = 1
Status.RUNTIME_ERROR = 2
Status.OOM = 3
Status.DEAD = 4

local NativeResult = {}
NativeResult.OK = 0
NativeResult.ERROR = 1
NativeResult.YIELD = 2
NativeResult.OOM = 3
NativeResult.STACK_GROW = 4

local Err = {}
Err.NONE = 0
Err.RUNTIME = 1
Err.SYNTAX = 2
Err.MEMORY = 3
Err.HANDLER = 4
Err.YIELD = 5
Err.BAD_OPCODE = 6
Err.STACK_OVERFLOW = 7
Err.C_STACK_OVERFLOW = 8
Err.TYPE = 9
Err.ARITH = 10
Err.COMPARE = 11
Err.CONCAT = 12
Err.INDEX = 13
Err.CALL = 14
Err.LOOP = 15
Err.API = 16

local ProtoFlag = {}
ProtoFlag.PF_VAHID = 1  -- function has hidden vararg arguments (set by VARARGPREP)
ProtoFlag.PF_VATAB = 2  -- vararg passed as table (cleared after VARARGPREP runs)
ProtoFlag.PF_FIXED = 4  -- prototype has parts in fixed memory (read-only hint)

local FrameFlag = {}
FrameFlag.YIELDABLE = 1
FrameFlag.PROTECTED = 2
FrameFlag.NATIVE = 4

local ThreadFlag = {}
ThreadFlag.YIELDABLE = 1
ThreadFlag.IN_PROTECTED = 2
ThreadFlag.CLOSING = 4

local GCColor = {}
GCColor.WHITE0 = 0
GCColor.WHITE1 = 1
GCColor.GRAY = 2
GCColor.BLACK = 3

local GCState = {}
GCState.PAUSE = 0
GCState.PROPAGATE = 1
GCState.SWEEP = 2
GCState.FINALIZE = 3

local MAX_STACK_SIZE = 1000000
local MAX_FRAMES = 1000

local Abi = {}
Abi.VM_VERSION = 1
Abi.NATIVE_VERSION = 1
Abi.VALIDATOR_VERSION = 1

return {
    Tag = Tag,
    Op = Op,
    TM = TM,
    Resume = Resume,
    Status = Status,
    NativeResult = NativeResult,
    Err = Err,
    ProtoFlag = ProtoFlag,
    FrameFlag = FrameFlag,
    ThreadFlag = ThreadFlag,
    GCColor = GCColor,
    GCState = GCState,
    Abi = Abi,
    MAX_STACK_SIZE = MAX_STACK_SIZE,
    MAX_FRAMES = MAX_FRAMES,
}
